gridemic/__init__.py
gridemic/gridemic.py
gridemic-1.1.dist-info/METADATA
gridemic-1.1.dist-info/WHEEL
gridemic-1.1.dist-info/licenses/LICENSE
gridemic-1.1.dist-info/RECORD
