Metadata-Version: 2.1
Name: gridemic
Version: 1.1
Summary: A python package for simulating stochastic agent-based epidemic models on a square grid with long-range interactions.
Project-URL: Homepage, https://github.com/burakbudanur/gridemic
Project-URL: Bug Tracker, https://github.com/burakbudanur/gridemic/issues
Author-email: Nazmi Burak Budanur <nbudanur@pks.mpg.de>
License-File: LICENSE
Classifier: License :: OSI Approved :: MIT License
Classifier: Operating System :: OS Independent
Classifier: Programming Language :: Python :: 3
Requires-Python: >=3.7
